keycloak_xss/__init__.py
keycloak_xss/main.py
keycloak_xss/includes/__init__.py
keycloak_xss/includes/bot.py
keycloak_xss/includes/filereader.py
keycloak_xss/includes/scan.py
keycloak_xss/includes/writefile.py
keycloak_xss/utils/__init__.py
keycloak_xss/utils/configure.py
keycloak_xss/utils/const.py
keycloak_xss/utils/helpers.py
keycloak_xss-1.2.dist-info/METADATA
keycloak_xss-1.2.dist-info/WHEEL
keycloak_xss-1.2.dist-info/entry_points.txt
keycloak_xss-1.2.dist-info/top_level.txt
keycloak_xss-1.2.dist-info/RECORD
