Metadata-Version: 2.1
Name: keycloak-xss
Version: 1.2
Requires-Dist: click
Requires-Dist: pyyaml
Requires-Dist: requests
